LICENSE
MANIFEST.in
README.md
setup.py
dash_pivottable/PivotTable.py
dash_pivottable/__init__.py
dash_pivottable/_imports_.py
dash_pivottable/dash_pivottable.dev.js
dash_pivottable/dash_pivottable.min.js
dash_pivottable/metadata.json
dash_pivottable/package.json
tests/test_callbacks.py
tests/test_percy.py
trialzen_dash_pivottable.egg-info/PKG-INFO
trialzen_dash_pivottable.egg-info/SOURCES.txt
trialzen_dash_pivottable.egg-info/dependency_links.txt
trialzen_dash_pivottable.egg-info/requires.txt
trialzen_dash_pivottable.egg-info/top_level.txt