Metadata-Version: 2.1
Name: trialzen-dash-pivottable
Version: 0.0.83
Summary: Implementation of react-pivottable in Dash (Python)
Author: Xing Han Lu <xinghan@plotly.com>
License: MIT
License-File: LICENSE
